{
  "meeting_date": "2025-05-01T08:02:12.600000-05:00",
  "meeting_status": "COMPLETED",
  "meeting_title": "Onboarding meeting with Duplication family",
  "meeting_type": "ONBOARDING",
  "sections": [
    {
      "header": "Summary",
      "sections": [
        {
          "id": "881307f7-abde-463f-a850-a20282773fc3",
          "name": "Summary",
          "header": "Summary",
          "description": "",
          "order_no": 0,
          "unstructured_facts": [
            {
              "id": "b9ac0c3b-3cd8-483e-9e7c-d1ec15c5ceb5",
              "content": "Discussed the significant dental expenses incurred, totalling over £8,000, and the impact on personal finances.",
              "order_no": 0,
              "status": "VERIFIED"
            },
            {
              "id": "347bef54-5132-4103-9e88-b53a5d4eaa34",
              "content": "Reviewed ongoing health concerns, including recent scans and upcoming day surgery for a skin issue, with regular check-ups by skincare nurses and consultants.",
              "order_no": 1,
              "status": "VERIFIED"
            },
            {
              "id": "615e64e9-c33b-45ad-b4ca-b6351b0f6064",
              "content": "Explored holiday plans and the challenges of obtaining travel insurance due to pre-existing health conditions, with a mention of a company called AllClear that provided coverage.",
              "order_no": 2,
              "status": "VERIFIED"
            },
            {
              "id": "32330bf4-c3ed-4cbd-b8a7-a8ddd3b119b4",
              "content": "Updated on the status of the will, which has been redone, but faced issues with inaccuracies from the legal firm, leading to dissatisfaction with their service.",
              "order_no": 3,
              "status": "VERIFIED"
            },
            {
              "id": "394e0b71-50b3-4a58-a679-ba09ac0d6e7d",
              "content": "Reviewed financial position, highlighting a healthy investment portfolio with a growth of £16,108 over the last year, and discussed the impact of potential care costs on future finances.",
              "order_no": 4,
              "status": "VERIFIED"
            },
            {
              "id": "8e4c8496-6b5a-4439-a661-43287c6c4c48",
              "content": "Explored the use of a trust fund and property as potential resources for future care needs, with a focus on maintaining financial stability.",
              "order_no": 5,
              "status": "VERIFIED"
            },
            {
              "id": "8e064ad0-a908-442c-8366-5c84e5cac8cb",
              "content": "Discussed the use of a client portal for accessing financial documents and updates, with a demonstration of how to register and use the portal.",
              "order_no": 6,
              "status": "VERIFIED"
            }
          ],
          "structured_facts": []
        }
      ]
    },
    {
      "header": "Relationship Building",
      "sections": [
        {
          "id": "f58a8516-6230-42ca-a226-db354f822022",
          "name": "Relationship Building Facts",
          "header": "Relationship Building",
          "description": "",
          "order_no": 0,
          "unstructured_facts": [
            {
              "id": "c9434103-12ca-4280-a0fd-1d60a5b6138e",
              "content": "Liz enjoys walking and exercise but was limited due to an open wound from surgery, which affected her ability to engage in these activities.",
              "order_no": 0,
              "status": "VERIFIED"
            },
            {
              "id": "d5e5386a-adc2-4018-89b5-57a6c5c6259b",
              "content": "Liz has a holiday planned in May with her family, including her brother, his wife, her nephew, and great-nephews. They have separate accommodations to maintain independence during the trip.",
              "order_no": 1,
              "status": "VERIFIED"
            },
            {
              "id": "a6228eec-0bdd-4fb4-b7f2-3a2aa8cd688b",
              "content": "Liz is planning a trip to Lutford with a friend in June to visit gardens, using a farmhouse B&B she previously enjoyed.",
              "order_no": 2,
              "status": "VERIFIED"
            },
            {
              "id": "a87ef8cb-b9f6-4f59-9735-ad2f8b2b5a87",
              "content": "Liz has a strong relationship with her nephew and great-nephews, who are three years old and one year old. Her nephew runs his own business and is under pressure due to family and work commitments.",
              "order_no": 3,
              "status": "VERIFIED"
            }
          ],
          "structured_facts": []
        }
      ]
    },
    {
      "header": "Discussion",
      "sections": [
        {
          "id": "1ef48664-0cd1-4838-ae74-b2de1ab3b7a3",
          "name": "Soft Facts Discussed",
          "header": "Discussion",
          "description": "",
          "order_no": 14,
          "unstructured_facts": [
            {
              "id": "32bf4f8a-081c-4df0-8feb-cd942a005ca3",
              "content": "Liz undergoes regular health checks every six months, alternating between skincare nurses and a consultant, due to her history with cancer. Recently, a mole was identified on her neck, which the consultant decided to remove through day surgery scheduled for the end of February. Liz had a previous surgery where non-dissolvable stitches were unexpectedly found, causing complications. This required another operation under local anaesthetic, which was almost converted to a general anaesthetic due to the depth required.",
              "order_no": 0,
              "status": "VERIFIED"
            },
            {
              "id": "52968922-5b33-48e2-a09c-6e2a2869cb31",
              "content": "Liz has experienced more health issues this winter, including frequent colds and coughs, which she attributes to a potentially weakened immune system. She is concerned about her health and longevity, especially after undergoing immunotherapy.",
              "order_no": 1,
              "status": "VERIFIED"
            },
            {
              "id": "bb467844-b5f6-4ede-ac04-690e4a3b73f6",
              "content": "Liz has concerns about the potential impact of dementia on her decision-making abilities in the future.",
              "order_no": 2,
              "status": "VERIFIED"
            },
            {
              "id": "d9c5b420-9e1c-47c9-8fb8-03f20baea307",
              "content": "Liz has experienced melanoma and is aware of the potential for it to spread, but feels there would be time for conversations if it progresses. She is also aware of the potential complications from lymph node removal and chose not to pursue that route initially.",
              "order_no": 3,
              "status": "VERIFIED"
            },
            {
              "id": "2dd498d9-6a5f-4c2e-aac1-1922cfb55b64",
              "content": "Liz's brother, Charles, has health issues, which may affect his ability to join the family holiday in Menorca.",
              "order_no": 4,
              "status": "VERIFIED"
            },
            {
              "id": "a571da04-255c-4275-a166-525f14ad752f",
              "content": "Liz mentioned a case involving a woman whose son is autistic, requiring the money she receives to be protected and ring-fenced to ensure it does not affect his state benefits.",
              "order_no": 5,
              "status": "VERIFIED"
            },
            {
              "id": "267ae701-d65e-4b4c-8034-49bf3e90b15d",
              "content": "Liz uses a laptop primarily for emails and has limited storage capacity on her phone, which is nearly full.",
              "order_no": 6,
              "status": "VERIFIED"
            }
          ],
          "structured_facts": []
        },
        {
          "id": "fc0b3f51-2895-4b1a-9b60-91bf9d263b93",
          "name": "Client Queries & Concerns",
          "header": "Discussion",
          "description": "",
          "order_no": 15,
          "unstructured_facts": [
            {
              "id": "6ec55d8f-19d4-430b-b64d-f0cb25f87f18",
              "content": "Duplication is interested in receiving a business card from admin to refer someone who is likely to receive a significant payout due to medical mishandling.",
              "order_no": 0,
              "status": "VERIFIED"
            }
          ],
          "structured_facts": []
        },
        {
          "id": "dd85be1c-3124-4975-8e97-f8ece87a5323",
          "name": "Fees",
          "header": "Discussion",
          "description": "",
          "order_no": 16,
          "unstructured_facts": [
            {
              "id": "562f8d0b-3404-4c6e-aaac-e6f2c9503b51",
              "content": "The Duplication family's investment costs have decreased from 1.53% to 1.33% over the past year, resulting in a reduction of fees from £2,289 to an estimated £1,953.",
              "order_no": 0,
              "status": "VERIFIED"
            }
          ],
          "structured_facts": []
        }
      ]
    },
    {
      "header": "Financial Plans",
      "sections": [
        {
          "id": "71fa4dec-2272-46a1-b286-1c3c99ddf619",
          "name": "Goals",
          "header": "Financial Plans",
          "description": "",
          "order_no": 1,
          "unstructured_facts": [
            {
              "id": "b406ea7e-0ae9-4c51-8611-46a020392e10",
              "content": "Liz's financial goal is for her investments to provide her with £400 a month, and she has been withdrawing money regularly to ensure she has enough in her bank account for her needs.",
              "order_no": 0,
              "status": "VERIFIED"
            },
            {
              "id": "8d4d6176-1893-4b30-aee7-d2ceab7f2165",
              "content": "Liz is considering moving to Dorchester to be closer to a train line and the coast, which she has always lived near. This move is also considered in case she can no longer drive.",
              "order_no": 1,
              "status": "VERIFIED"
            }
          ],
          "structured_facts": []
        },
        {
          "id": "e7625eba-ad1e-4156-8ddc-84858bfc2bc3",
          "name": "Cashflow Planning",
          "header": "Financial Plans",
          "description": "",
          "order_no": 3,
          "unstructured_facts": [
            {
              "id": "8e2edc52-4b9e-4245-bcc0-8f205ce17ccc",
              "content": "Liz's income and expenditure are closely matched, with £1,455 coming in monthly and £1,382 being spent, including holidays.",
              "order_no": 0,
              "status": "VERIFIED"
            },
            {
              "id": "4b79336e-d9b2-4359-8f8f-9b65385ed8f0",
              "content": "Liz's financial projections indicate that her invested money would run out around age 88-89, but she is currently in a healthy financial position.",
              "order_no": 1,
              "status": "VERIFIED"
            }
          ],
          "structured_facts": []
        },
        {
          "id": "71c1f100-6c6b-4e45-a320-e0c6af555124",
          "name": "Estate Planning",
          "header": "Financial Plans",
          "description": "",
          "order_no": 4,
          "unstructured_facts": [
            {
              "id": "cbe3af5a-7e25-410c-9d6b-74a72a04b6ff",
              "content": "Liz has recently redone her will, but faced issues with inaccuracies from her solicitors, Rachel and Tracy, including incorrect names and burial preferences. Her nephew's wife, a trained barrister, reviewed it to ensure accuracy.",
              "order_no": 0,
              "status": "VERIFIED"
            },
            {
              "id": "19ca9905-301a-43c1-a92b-c6478aaff090",
              "content": "Liz believes her beneficiaries will face a significant inheritance tax burden, and she is considering spending her money on personal needs rather than leaving it to be taxed. Her main priority is to live the life she wants rather than focusing on saving money for tax purposes.",
              "order_no": 1,
              "status": "VERIFIED"
            },
            {
              "id": "955acaec-3b95-4de8-88c8-73dc10b2538a",
              "content": "Liz's estate is liable for inheritance tax, and she has a will that has now been updated.",
              "order_no": 2,
              "status": "VERIFIED"
            },
            {
              "id": "3b78dc77-442b-412a-b688-f398abf19f47",
              "content": "Liz's nephew and brother are involved in a trust fund that she can access if needed, particularly for care expenses.",
              "order_no": 3,
              "status": "VERIFIED"
            },
            {
              "id": "cf1d6195-7baf-48a9-a106-f78de2ebfcab",
              "content": "Liz has been advised to have a conversation with her nephew and brother about the trust fund and to document her wishes in case she is unable to make decisions in the future due to conditions like dementia.",
              "order_no": 4,
              "status": "VERIFIED"
            }
          ],
          "structured_facts": []
        },
        {
          "id": "54a48186-0743-488c-9055-c9dfed6242f7",
          "name": "Assets",
          "header": "Financial Plans",
          "description": "",
          "order_no": 5,
          "unstructured_facts": [
            {
              "id": "fd1f355f-787b-401c-811b-88f61240121c",
              "content": "Liz has invested between £14,000 and £15,000 in holiday property bonds, which she plans to use for her upcoming trip to Menorca.",
              "order_no": 0,
              "status": "VERIFIED"
            },
            {
              "id": "619246b3-9b34-4774-a20f-0c86d7cb244f",
              "content": "Liz has approximately £14,000 in her savings account, with £5,000 earmarked for dental expenses and potential building repairs.",
              "order_no": 1,
              "status": "VERIFIED"
            },
            {
              "id": "6300ccf0-7493-44ee-8f5c-0a961a2b6330",
              "content": "Liz's assets include a property valued at approximately £500,000, long-term investments worth £146,000, and cash holdings around £62,000.",
              "order_no": 2,
              "status": "VERIFIED"
            },
            {
              "id": "b002f7c9-3ac3-4117-95e3-524d6453cbdc",
              "content": "Liz has a trust fund managed by her nephew and brother, estimated to be over £100,000, which she can access if needed. She has not included it in her financial planning as she does not currently need it, but intends to use it when she requires care.",
              "order_no": 3,
              "status": "VERIFIED"
            },
            {
              "id": "807088b3-0ca0-44b9-9d90-71905b9837f4",
              "content": "Liz's nephew borrowed £20,000 to buy a house, and Liz does not intend to reclaim this money unless she runs short of funds.",
              "order_no": 4,
              "status": "VERIFIED"
            },
            {
              "id": "8a681786-966f-4eae-a86c-af1b5cc54bf7",
              "content": "Liz's investment portfolio has grown from £142,000 to £146,000 over the past year, with a total return of £16,108, which is an 11.8% return. This includes £12,800 in withdrawals.",
              "order_no": 5,
              "status": "VERIFIED"
            }
          ],
          "structured_facts": []
        },
        {
          "id": "5db4ab3c-2380-4244-9214-065b968bf2d4",
          "name": "Income",
          "header": "Financial Plans",
          "description": "",
          "order_no": 6,
          "unstructured_facts": [
            {
              "id": "0daead4e-e26d-4a42-8848-876095bb133c",
              "content": "The Duplication family receives a state pension every four weeks, with 13 payments per year, which has increased significantly due to the triple lock mechanism.",
              "order_no": 0,
              "status": "VERIFIED"
            }
          ],
          "structured_facts": []
        },
        {
          "id": "22d7ec7f-5969-4fd1-9447-8a2399970a83",
          "name": "Expenditures",
          "header": "Financial Plans",
          "description": "",
          "order_no": 7,
          "unstructured_facts": [
            {
              "id": "08821dd0-b6b2-4e47-bcd9-506a5ed4f278",
              "content": "Liz has spent just over £8,000 on dental work, including an implant and further dental appointments due to a broken tooth over Christmas.",
              "order_no": 0,
              "status": "VERIFIED"
            },
            {
              "id": "9418ca51-0d1d-4427-8964-1e61d9e229db",
              "content": "Liz is considering downsizing her property in the future due to maintenance costs and the size of the land, which is about a third of an acre. She recently spent nearly £1,000 on hedge and tree maintenance.",
              "order_no": 1,
              "status": "VERIFIED"
            }
          ],
          "structured_facts": []
        },
        {
          "id": "54066873-2f4c-4bd6-990c-db7e296ee4cf",
          "name": "Insurance Needs",
          "header": "Financial Plans",
          "description": "",
          "order_no": 9,
          "unstructured_facts": [
            {
              "id": "70e122f9-adcc-4ada-912f-05b602eedd34",
              "content": "Liz finds obtaining holiday insurance challenging due to her medical history, but she managed to secure coverage through AllClear after clarifying her medical conditions.",
              "order_no": 0,
              "status": "VERIFIED"
            }
          ],
          "structured_facts": []
        },
        {
          "id": "b77ef70c-4705-426b-82f4-f3583e228891",
          "name": "Tax Planning",
          "header": "Financial Plans",
          "description": "",
          "order_no": 10,
          "unstructured_facts": [
            {
              "id": "76ff9565-5b1d-4dd7-b452-4c2e3c3797e3",
              "content": "The Duplication family is aware that their estate is liable for inheritance tax, but their main priority is to live the life they want rather than focusing on saving money for tax purposes.",
              "order_no": 0,
              "status": "VERIFIED"
            }
          ],
          "structured_facts": []
        },
        {
          "id": "876a4f5c-c518-4f59-9c60-8ea4d8df6bfb",
          "name": "Investment Preferences",
          "header": "Financial Plans",
          "description": "",
          "order_no": 12,
          "unstructured_facts": [
            {
              "id": "15b9acfe-8487-4bca-9a91-180d31112ce4",
              "content": "The Duplication family's investment portfolio is diversified with £17,416 in different investments, comprising 60% in equities and 40% in fixed interest. The portfolio is heavily weighted towards British companies, with 50% of the portfolio in the UK.",
              "order_no": 0,
              "status": "VERIFIED"
            }
          ],
          "structured_facts": []
        },
        {
          "id": "f27fbb46-d8da-407b-a419-296c0e4ac8ce",
          "name": "Knowledge And Experience",
          "header": "Financial Plans",
          "description": "",
          "order_no": 13,
          "unstructured_facts": [
            {
              "id": "8c1effc8-aed0-44ab-9207-e26426cc7d83",
              "content": "Admin explained the process of registering for the client portal, including accessing it via a laptop, phone, or iPad, and provided step-by-step guidance on how to log in and navigate the portal.",
              "order_no": 0,
              "status": "VERIFIED"
            }
          ],
          "structured_facts": []
        }
      ]
    },
    {
      "header": "Vulnerabilities",
      "sections": [
        {
          "id": "75c86d69-1a18-4123-be2a-4aba5f2b48e3",
          "name": "Health",
          "header": "Vulnerabilities",
          "description": "",
          "order_no": 0,
          "unstructured_facts": [
            {
              "id": "455e8e2d-e91a-4efe-9abd-ef9aa6019bae",
              "content": "Critical health vulnerability affecting financial decisions due to recurring melanoma treatments and immunotherapy side effects, leading to a weakened immune system and frequent infections as reported by the client.",
              "order_no": 0,
              "status": "VERIFIED"
            }
          ],
          "structured_facts": []
        },
        {
          "id": "7a6ccbd7-1e22-4443-9db9-adeded6c7167",
          "name": "Financial Resilience",
          "header": "Vulnerabilities",
          "description": "",
          "order_no": 2,
          "unstructured_facts": [
            {
              "id": "75c4d92e-27bd-48ea-8ab9-6fb12a4325ec",
              "content": "Potential long-term care cost vulnerability impacting financial resilience, as projections indicate asset depletion during later years coupled with uncertainties around trust fund values for care funding.",
              "order_no": 0,
              "status": "VERIFIED"
            }
          ],
          "structured_facts": []
        },
        {
          "id": "7483b3a5-d3d6-48f5-a16d-cd7dfba88ac8",
          "name": "Emotional Resilience",
          "header": "Vulnerabilities",
          "description": "",
          "order_no": 3,
          "unstructured_facts": [
            {
              "id": "71116a18-5fb5-431b-96d8-f37dcd21a9d4",
              "content": "Potential mental health vulnerability affecting decision-making, indicated by the client’s occasional low mood comments and limited emotional support from family, which may impair his ability to navigate complex financial matters.",
              "order_no": 0,
              "status": "VERIFIED"
            }
          ],
          "structured_facts": []
        },
        {
          "id": "286ab7c8-5103-4313-a2f4-9eebc70ddebb",
          "name": "Capability",
          "header": "Vulnerabilities",
          "description": "",
          "order_no": 4,
          "unstructured_facts": [
            {
              "id": "6c7346ec-4132-4b18-9339-d12580a40652",
              "content": "Potential digital capability vulnerability impacting engagement with financial communications, as the client expressed confusion and admitted not being highly proficient with digital platforms when accessing documents.",
              "order_no": 0,
              "status": "VERIFIED"
            }
          ],
          "structured_facts": []
        }
      ]
    },
    {
      "header": "Risks",
      "sections": [
        {
          "id": "0eea3057-4d53-417a-b1d1-0cc5e9174b87",
          "name": "Risk Tolerance",
          "header": "Risks",
          "description": "",
          "order_no": 0,
          "unstructured_facts": [
            {
              "id": "c7be0436-cd26-4be8-8ec6-0564a697ac72",
              "content": "The Duplication family has a moderate risk tolerance, indicated by their comfort with a risk profile of 5 out of 10. They mentioned, 'I'm in low to medium level 5 or something, I think it was. So I'm nearer the medium than I am.' This suggests they are comfortable with some level of risk but not extreme fluctuations.",
              "order_no": 0,
              "status": "VERIFIED"
            }
          ],
          "structured_facts": []
        },
        {
          "id": "26d10929-b4e8-44cb-a2b0-2385b97b6871",
          "name": "Capacity For Loss",
          "header": "Risks",
          "description": "",
          "order_no": 1,
          "unstructured_facts": [
            {
              "id": "b5c457b3-5a6b-480b-84ec-6c7ae6fbd203",
              "content": "The Duplication family has a capacity for loss of 15.64%, as discussed in the meeting. The adviser mentioned, 'I'm expecting you to lose £15,640' in a market downturn scenario, which aligns with their risk profile of 5 out of 10.",
              "order_no": 0,
              "status": "VERIFIED"
            },
            {
              "id": "c7f6f709-1659-49c7-adac-3ee2c03ce896",
              "content": "The Duplication family has a cautious approach to spending and financial planning, as evidenced by their focus on maintaining a balance between income and expenditure. They stated, 'I've still got over. I think I've got, in fact in my savings account about 14 grand. But about 5 of that is going to go out in dental and a.' This indicates careful management of finances to ensure liquidity for unexpected expenses.",
              "order_no": 1,
              "status": "VERIFIED"
            },
            {
              "id": "c8d359e9-9e0b-477d-bb9b-51f380991138",
              "content": "The Duplication family shows a conservative approach to financial planning, prioritizing essential expenses and potential future care costs. They mentioned, 'I'll need every penny that I've got, sort of.' This suggests a focus on preserving capital for future needs, indicating a lower capacity for loss.",
              "order_no": 2,
              "status": "VERIFIED"
            },
            {
              "id": "98592dde-b53a-4d76-afb2-683957b5de17",
              "content": "The Duplication family has a potential safety net in the form of a trust fund, which could enhance their capacity for loss. They stated, 'But what doesn't come into this equation and I don't know the sum that's in there. It's a trust fund that I've got access to.' This indicates an additional financial resource that could be utilized if necessary.",
              "order_no": 3,
              "status": "VERIFIED"
            }
          ],
          "structured_facts": []
        }
      ]
    },
    {
      "header": "Other",
      "sections": []
    }
  ]
}
